jupyterlab_theme_minimalist/__init__.py
jupyterlab_theme_minimalist/_version.py
jupyterlab_theme_minimalist/labextension/package.json
jupyterlab_theme_minimalist/labextension/static/549.b519aad782a120040a91.js
jupyterlab_theme_minimalist/labextension/static/568.a8183cae730819bd191f.js
jupyterlab_theme_minimalist/labextension/static/remoteEntry.d61daa90c73ee645dc34.js
jupyterlab_theme_minimalist/labextension/static/style.js
jupyterlab_theme_minimalist/labextension/themes/jupyterlab_theme_minimalist/index.css
jupyterlab_theme_minimalist/labextension/themes/jupyterlab_theme_minimalist/index.js
jupyterlab_theme_minimalist-0.1.0.data/data/share/jupyter/labextensions/jupyterlab_theme_minimalist/install.json
jupyterlab_theme_minimalist-0.1.0.data/data/share/jupyter/labextensions/jupyterlab_theme_minimalist/package.json
jupyterlab_theme_minimalist-0.1.0.data/data/share/jupyter/labextensions/jupyterlab_theme_minimalist/static/549.b519aad782a120040a91.js
jupyterlab_theme_minimalist-0.1.0.data/data/share/jupyter/labextensions/jupyterlab_theme_minimalist/static/568.a8183cae730819bd191f.js
jupyterlab_theme_minimalist-0.1.0.data/data/share/jupyter/labextensions/jupyterlab_theme_minimalist/static/remoteEntry.d61daa90c73ee645dc34.js
jupyterlab_theme_minimalist-0.1.0.data/data/share/jupyter/labextensions/jupyterlab_theme_minimalist/static/style.js
jupyterlab_theme_minimalist-0.1.0.data/data/share/jupyter/labextensions/jupyterlab_theme_minimalist/themes/jupyterlab_theme_minimalist/index.css
jupyterlab_theme_minimalist-0.1.0.data/data/share/jupyter/labextensions/jupyterlab_theme_minimalist/themes/jupyterlab_theme_minimalist/index.js
jupyterlab_theme_minimalist-0.1.0.dist-info/LICENSE
jupyterlab_theme_minimalist-0.1.0.dist-info/METADATA
jupyterlab_theme_minimalist-0.1.0.dist-info/WHEEL
jupyterlab_theme_minimalist-0.1.0.dist-info/top_level.txt
jupyterlab_theme_minimalist-0.1.0.dist-info/RECORD
