Metadata-Version: 2.1
Name: jupyterlab-theme-minimalist
Version: 0.1.0
Summary: A minimalistic theme for jupyterlab
Home-page: https://github.com/max-grzanna/jupyterlab_minimalist
Author: Max Grzanna
License: BSD-3-Clause
Keywords: Jupyter,JupyterLab
Platform: Linux
Platform: Mac OS X
Platform: Windows
Classifier: License :: OSI Approved :: BSD License
Classifier: Programming Language :: Python
Classifier: Programming Language :: Python :: 3
Classifier: Programming Language :: Python :: 3.6
Classifier: Programming Language :: Python :: 3.7
Classifier: Programming Language :: Python :: 3.8
Classifier: Framework :: Jupyter
Requires-Python: >=3.6
License-File: LICENSE
Requires-Dist: jupyterlab (==3.*,>=3.0.0)
